link/__init__.py
link/base.py
link/canhandle.py
link/ccp.py
link/constants.py
link/dfu.py
link/isotp.py
link/serial.py
link/spi.py
link/uds.py
link/usb.py
link/utils.py
link/xcp.py
carlink-0.0.13.dist-info/METADATA
carlink-0.0.13.dist-info/WHEEL
carlink-0.0.13.dist-info/top_level.txt
carlink-0.0.13.dist-info/RECORD
